[
  {
    "question_id": 190,
    "text": "During a meeting between lead engineer Tom and driver Christina, engineer Max states that he has finally read the rules and found a legal way to save weight. What suggestion could Max have made?",
    "type": "single-choice",
    "time": 0,
    "answer_options": [
      {
        "answer_id": 739,
        "question_id": 190,
        "answer_text": "Design a new helmet for Christina that reduces driver gear weight by 0,450 kilograms.",
        "is_correct": false
      },
      {
        "answer_id": 740,
        "question_id": 190,
        "answer_text": "Design a new scatter shield to protect their non-metallic chain from 2mm Aluminium. This saves 120 grams",
        "is_correct": false
      },
      {
        "answer_id": 741,
        "question_id": 190,
        "answer_text": "Replacing the aluminium brake pedal with a shiny titanium version that saves 0,14kg",
        "is_correct": false
      },
      {
        "answer_id": 742,
        "question_id": 190,
        "answer_text": "Replacing the shoulder belts with new 40mm belts that also suit Christina's HANS device and saves 83 grams",
        "is_correct": false
      }
    ],
    "solutions": [],
    "question_images": [],
    "answers": [
      {
        "answer_id": 739,
        "question_id": 190,
        "answer_text": "Design a new helmet for Christina that reduces driver gear weight by 0,450 kilograms.",
        "is_correct": false
      },
      {
        "answer_id": 740,
        "question_id": 190,
        "answer_text": "Design a new scatter shield to protect their non-metallic chain from 2mm Aluminium. This saves 120 grams",
        "is_correct": false
      },
      {
        "answer_id": 741,
        "question_id": 190,
        "answer_text": "Replacing the aluminium brake pedal with a shiny titanium version that saves 0,14kg",
        "is_correct": false
      },
      {
        "answer_id": 742,
        "question_id": 190,
        "answer_text": "Replacing the shoulder belts with new 40mm belts that also suit Christina's HANS device and saves 83 grams",
        "is_correct": false
      }
    ],
    "quiz_ids": [
      19
    ],
    "years": [
      "2018"
    ],
    "countries": [
      "Netherlands"
    ],
    "events": [
      "Formula Student Netherlands"
    ]
  },
  {
    "question_id": 191,
    "text": "What is the objective of the technical inspection at FSN2018?",
    "type": "single-choice",
    "time": 0,
    "answer_options": [
      {
        "answer_id": 743,
        "question_id": 191,
        "answer_text": "To determine if the vehicle is able to participate in dynamic events and is compliant to the rules",
        "is_correct": false
      },
      {
        "answer_id": 744,
        "question_id": 191,
        "answer_text": "To ensure all cars are compliant before the event starts",
        "is_correct": false
      },
      {
        "answer_id": 745,
        "question_id": 191,
        "answer_text": "To determine if the team has a proper understanding of the rules",
        "is_correct": false
      },
      {
        "answer_id": 746,
        "question_id": 191,
        "answer_text": "To ensure a safe event",
        "is_correct": false
      }
    ],
    "solutions": [],
    "question_images": [],
    "answers": [
      {
        "answer_id": 743,
        "question_id": 191,
        "answer_text": "To determine if the vehicle is able to participate in dynamic events and is compliant to the rules",
        "is_correct": false
      },
      {
        "answer_id": 744,
        "question_id": 191,
        "answer_text": "To ensure all cars are compliant before the event starts",
        "is_correct": false
      },
      {
        "answer_id": 745,
        "question_id": 191,
        "answer_text": "To determine if the team has a proper understanding of the rules",
        "is_correct": false
      },
      {
        "answer_id": 746,
        "question_id": 191,
        "answer_text": "To ensure a safe event",
        "is_correct": false
      }
    ],
    "quiz_ids": [
      19
    ],
    "years": [
      "2018"
    ],
    "countries": [
      "Netherlands"
    ],
    "events": [
      "Formula Student Netherlands"
    ]
  }
]